flash_attention_jax/__init__.py
flash_attention_jax/attention.py
flash_attention_jax/flash_attention.py
flash_attention_jax/rabe_attention.py
flash_attention_jax/utils.py
flash_attention_jax-0.0.1.dist-info/LICENSE
flash_attention_jax-0.0.1.dist-info/METADATA
flash_attention_jax-0.0.1.dist-info/WHEEL
flash_attention_jax-0.0.1.dist-info/top_level.txt
flash_attention_jax-0.0.1.dist-info/RECORD
